architector/__init__.py
architector/__main__.py
architector/_version.py
architector/arch_context_manage.py
architector/ase_db_utilities.py
architector/complex_construction.py
architector/geometries.py
architector/io_align_mol.py
architector/io_calc.py
architector/io_core.py
architector/io_crest.py
architector/io_lig.py
architector/io_molecule.py
architector/io_obabel.py
architector/io_process_input.py
architector/io_ptable.py
architector/io_symmetry.py
architector/io_xtb_calc.py
architector/vibrations_free_energy.py
architector/visualization.py
architector/data/angle_stats_datasource.csv
architector/data/ligtype_angle_reference.csv
architector-0.0.10.dist-info/LICENSE.txt
architector-0.0.10.dist-info/METADATA
architector-0.0.10.dist-info/WHEEL
architector-0.0.10.dist-info/top_level.txt
architector-0.0.10.dist-info/RECORD
