Metadata-Version: 2.1
Name: architector
Version: 0.0.10
Summary: The architector python package - for 3D inorganometallic complex design.
Author: Michael G. Taylor et al.
License: BSD 3-Clause License
Classifier: Development Status :: 4 - Beta
Classifier: Intended Audience :: Science/Research
Classifier: Programming Language :: Python :: 3
Classifier: Topic :: Scientific/Engineering :: Chemistry
License-File: LICENSE.txt
Requires-Dist: ase
Requires-Dist: numpy
Requires-Dist: py3Dmol
Requires-Dist: pynauty
Requires-Dist: scipy
Requires-Dist: pandas
Requires-Dist: mendeleev
